ciclopibot/__init__.py
ciclopibot/__main__.py
ciclopibot/bot.py
ciclopibot/ciclopi.py
ciclopibot/messages.py
ciclopibot/data/__init__.py
ciclopibot-1.2.6.dist-info/METADATA
ciclopibot-1.2.6.dist-info/WHEEL
ciclopibot-1.2.6.dist-info/top_level.txt
ciclopibot-1.2.6.dist-info/RECORD
