Metadata-Version: 2.1
Name: ciclopibot
Version: 1.2.6
Summary: Telegram bot based on `davtelepot` providing information about CicloPi, the public bike-sharing service in Pisa.
Home-page: https://gogs.davte.it/davte/ciclopibot
Author: Davide Testa
Author-email: davide@davte.it
License: GNU General Public License v3.0
Keywords: telegram bot python asyncio async aiohttp davtelepot ciclopi bikesharing bicincitta bicincittà pisa bike
Platform: any
Classifier: Development Status :: 5 - Production/Stable
Classifier: Environment :: Console
Classifier: Framework :: AsyncIO
Classifier: Intended Audience :: Developers
Classifier: License :: OSI Approved :: GNU General Public License v3 (GPLv3)
Classifier: Natural Language :: English
Classifier: Operating System :: OS Independent
Classifier: Programming Language :: Python :: 3 :: Only
Classifier: Topic :: Communications :: Chat
Requires-Python: >=3.5
Requires-Dist: davtelepot
